LICENSE
MANIFEST.in
README.rst
setup.py
docs/Makefile
docs/make.bat
docs/rtd_requirements.txt
docs/run_sphinx-apidoc.sh
docs/source/conf.py
docs/source/index.rst
docs/source/license.rst
docs/source/modules.rst
docs/source/api/goparser.annotation.rst
docs/source/api/goparser.parser.rst
docs/source/api/goparser.term.rst
docs/source/notebooks/Demo.ipynb
goparser/__init__.py
goparser/annotation.py
goparser/parser.py
goparser/term.py
goparser.egg-info/PKG-INFO
goparser.egg-info/SOURCES.txt
goparser.egg-info/dependency_links.txt
goparser.egg-info/pbr.json
goparser.egg-info/requires.txt
goparser.egg-info/top_level.txt