Metadata-Version: 1.1
Name: goparser
Version: 1.1.4
Summary: GOparser - A Python Framework for Working with Gene Ontology (GO) Terms and Annotations
Home-page: https://github.com/flo-compbio/goparser
Author: Florian Wagner
Author-email: florian.wagner@duke.edu
License: GPLv3
Keywords: gene ontology biology bioinformatics
Platform: UNKNOWN
Classifier: Development Status :: 3 - Alpha
Classifier: Intended Audience :: Developers
Classifier: Intended Audience :: Science/Research
Classifier: Topic :: Scientific/Engineering :: Bio-Informatics
Classifier: License :: OSI Approved :: GNU General Public License v3 (GPLv3)
Classifier: Programming Language :: Python :: 2.7
